[
	{
		"benefitName": "Language Training",
		"languageTrainingEmployee": {
		"maxNumOfHours": "2",
		"selfLearningTool": "Yes",
		"maxAmt": "10005678.28",
		"currency": "U.S. Dollar",
		"grossUp": "Yes",
		"reimbursedBy": "Other",
		"reimbursedByOther": "Reimbursed by other",
		"comments": "Comments for Language Training Employee."
		},
		"languageTrainingFamily": {
		"maxNumOfHrsPerPerson": "2",
		"maxNumOfHrsPerFamily": "10",
		"selfLearningTool": "Yes",
		"maxAmt": "40008765.25",
		"currency": "U.S. Dollar",
		"grossUp": "Yes",
		"reimbursedBy": "Aires",
		"reimbursedByOther": "Reimbursed by other",
		"comments": "Comments for Language Training Family."		
		}
	}
]